MANIFEST.in
README.txt
setup.py
JitsiProvS.egg-info/PKG-INFO
JitsiProvS.egg-info/SOURCES.txt
JitsiProvS.egg-info/dependency_links.txt
JitsiProvS.egg-info/requires.txt
JitsiProvS.egg-info/top_level.txt
jitsiprovs/__init__.py
jitsiprovs/dbdata.py
jitsiprovs/jpapp.py
jitsiprovs/libdata.py
jitsiprovs/libprovisioner.py
jitsiprovs/provisioner.py
jitsiprovs/rootapp.py
scripts/jitsiprovs
scripts/jitsiprovs.debinit