Metadata-Version: 1.0
Name: JitsiProvS
Version: 0.10b1
Summary: Jitsi Provisioning Server
Home-page: http://www.itsyscom.com
Author: Dan-Cristian Bogos
Author-email: dan@itsyscom.com
License: GPLv3
Keywords: telecommunications voip
Platform: UNKNOWN
Classifier: Development Status :: 4 - Beta
Classifier: License :: OSI Approved :: GNU General Public License (GPL)
Classifier: Programming Language :: Python
Classifier: Intended Audience :: Telecommunications Industry
Classifier: Development Status :: 1 - Planning
Classifier: Topic :: Internet
Classifier: Operating System :: OS Independent
